setup.py
slojsonrpc/__init__.py
slojsonrpc.egg-info/PKG-INFO
slojsonrpc.egg-info/SOURCES.txt
slojsonrpc.egg-info/dependency_links.txt
slojsonrpc.egg-info/requires.txt
slojsonrpc.egg-info/top_level.txt