Metadata-Version: 1.1
Name: slojsonrpc
Version: 0.1
Summary: Universal JSONrpc handler, that maps class-methods to jsonrpc-methods.
Home-page: https://github.com/StefanLohmaier/slojsonrpc
Author: Stefan Lohmaier
Author-email: stefan.lohmaier@stefanlohmaier.de
License: UNKNOWN
Download-URL: https://github.com/StefanLohmaier/slojsonrpc/archive/0.1.zip
Keywords: jsonrpc
Platform: UNKNOWN
Classifier: Programming Language :: Python
Classifier: License :: OSI Approved :: MIT License
Classifier: Development Status :: 4 - Beta
Classifier: Environment :: Web Environment
Classifier: Topic :: Internet :: WWW/HTTP
Classifier: Topic :: Software Development :: Libraries :: Python Modules
